{
  "schema": "2.0.0",
  "generated_at": "2026-07-22T16:34:04.725052Z",
  "hypothesis": "common/<folder> is a provisional semantic merge unit",
  "game_version": "v1.37.5.0",
  "steam_build_id": 15918133,
  "executable_blake3": "612ad36554f05e66fb8901c6add85f5eaf45983c61440a3ed7d8fd3536a72873",
  "legacy_baseline_blake3": "6ed4b8332a97c279470f5022e63023ebba84d1fa5776daf02b5d64851921b223",
  "summary": {
    "expected_units": 12,
    "classified_units": 12,
    "full_denominator": true,
    "accepted_equivalent": 6,
    "manual_resolution_required": 2,
    "semantic_mismatch": 4,
    "failed": 0,
    "legacy_accepted": 1,
    "legacy_accepted_preserved": 1,
    "review_required": 6,
    "gate_passed": true,
    "elapsed_ms": 37398
  },
  "families": [
    {
      "content_family": "common/ages",
      "units": 1,
      "accepted_equivalent": 0,
      "review_required": true
    },
    {
      "content_family": "common/buildings",
      "units": 1,
      "accepted_equivalent": 0,
      "review_required": true
    },
    {
      "content_family": "common/governments",
      "units": 1,
      "accepted_equivalent": 0,
      "review_required": true
    },
    {
      "content_family": "common/institutions",
      "units": 1,
      "accepted_equivalent": 1,
      "review_required": false
    },
    {
      "content_family": "common/rebel_types",
      "units": 1,
      "accepted_equivalent": 0,
      "review_required": true
    },
    {
      "content_family": "common/religions",
      "units": 1,
      "accepted_equivalent": 1,
      "review_required": false
    },
    {
      "content_family": "common/scripted_effects",
      "units": 1,
      "accepted_equivalent": 0,
      "review_required": true
    },
    {
      "content_family": "common/scripted_triggers",
      "units": 4,
      "accepted_equivalent": 4,
      "review_required": false
    },
    {
      "content_family": "common/tradegoods",
      "units": 1,
      "accepted_equivalent": 0,
      "review_required": true
    }
  ],
  "units": [
    {
      "case_id": "3630876155",
      "snapshot_id": "d60369eb6a10122a1478df23c06031a84858075f09db11574e8d29cc1a260f5c",
      "relative_path": "common/rebel_types/zzz_foch_rebel_types.txt",
      "module_prefix": "common/rebel_types",
      "content_family": "common/rebel_types",
      "source_mod_ids": [
        "2164202838",
        "2185445645"
      ],
      "legacy_verdict": "diverges_structure",
      "legacy_accepted": false,
      "status": "semantic_mismatch",
      "publishable": false,
      "policies": {
        "merge_key_source": "assignment_key",
        "nested_merge_key_source": "assignment_key",
        "scalar": "conflict",
        "list": "union",
        "one_sided_removal": "remove",
        "block": "recursive",
        "boolean": "and",
        "block_patch": "recurse",
        "named_container": "conflict",
        "edit_wins_over_remove": false
      },
      "view_content_ids": {
        "base": "be509fb5209c1de6cf2d5b60254c89c783f3e9b878c1caf382d6c609aa3d9993",
        "left": "9cb6e70abfa679f7b6be41503c9809fe35dea2e78f673c6dca679747b5f1f562",
        "right": "c68a6ff605f62c68d0444d4354ff8d333aaa39083cfe0501d84ce07483604306",
        "human": "84ffc1716e8fe9eaf241f6a9af26279f24eba68ce002926510395d87c561462e"
      },
      "candidate_semantic_content_id": "07551107265be5a85dc7d78b6b5344aee0240b99c6d3b15bb55bdf2b0559c6e0",
      "base_definitions": 50,
      "active_definitions": 17,
      "missing_top_level_keys": [],
      "extra_top_level_keys": [
        "ita_monarchy_rebels",
        "ita_republican_rebels"
      ],
      "semantic_diff_from_human": {
        "left_atoms": 6280,
        "right_atoms": 6185,
        "shared_atoms": 6185,
        "left_only": {
          "assignment:ita_monarchy_rebels/assignment:area=text:nation": 1,
          "assignment:ita_monarchy_rebels/assignment:artillery=number:0.1": 1,
          "assignment:ita_monarchy_rebels/assignment:can_enforce_trigger/assignment:always=bool:yes": 1,
          "assignment:ita_monarchy_rebels/assignment:can_negotiate_trigger/assignment:always=bool:no": 1,
          "assignment:ita_monarchy_rebels/assignment:cavalry=number:0.4": 1,
          "assignment:ita_monarchy_rebels/assignment:color/item=number:180": 1,
          "assignment:ita_monarchy_rebels/assignment:color/item=number:25": 2,
          "assignment:ita_monarchy_rebels/assignment:defect_delay=number:60": 1,
          "assignment:ita_monarchy_rebels/assignment:defection=text:none": 1,
          "assignment:ita_monarchy_rebels/assignment:demands_description=text:ita_monarchy_rebels_demand": 1,
          "assignment:ita_monarchy_rebels/assignment:demands_enforced_effect/assignment:add_government_reform=text:autocracy_reform": 1,
          "assignment:ita_monarchy_rebels/assignment:demands_enforced_effect/assignment:add_government_reform=text:parliamentary_reform": 1,
          "assignment:ita_monarchy_rebels/assignment:demands_enforced_effect/assignment:add_prestige=number:-10": 1,
          "assignment:ita_monarchy_rebels/assignment:demands_enforced_effect/assignment:hidden_effect/assignment:clr_country_flag=text:ita_republican_matter": 1,
          "assignment:ita_monarchy_rebels/assignment:demands_enforced_effect/assignment:hidden_effect/assignment:set_country_flag=text:ita_republican_matter_subversed": 1,
          "assignment:ita_monarchy_rebels/assignment:demands_enforced_effect/assignment:if/assignment:change_government=text:monarchy": 1,
          "assignment:ita_monarchy_rebels/assignment:demands_enforced_effect/assignment:if/assignment:limit/assignment:NOT/assignment:government=text:monarchy": 1,
          "assignment:ita_monarchy_rebels/assignment:general=bool:yes": 1,
          "assignment:ita_monarchy_rebels/assignment:gfx_type=text:culture_province": 1,
          "assignment:ita_monarchy_rebels/assignment:government=text:any": 1,
          "assignment:ita_monarchy_rebels/assignment:handle_action_build_core=bool:yes": 1,
          "assignment:ita_monarchy_rebels/assignment:handle_action_change_culture=bool:yes": 1,
          "assignment:ita_monarchy_rebels/assignment:handle_action_negotiate=bool:yes": 1,
          "assignment:ita_monarchy_rebels/assignment:handle_action_send_missionary=bool:yes": 1,
          "assignment:ita_monarchy_rebels/assignment:handle_action_stability=bool:yes": 1,
          "assignment:ita_monarchy_rebels/assignment:independence=text:none": 1,
          "assignment:ita_monarchy_rebels/assignment:infantry=number:0.5": 1,
          "assignment:ita_monarchy_rebels/assignment:morale=number:1.1": 1,
          "assignment:ita_monarchy_rebels/assignment:movement_evaluation/assignment:factor=number:1": 1,
          "assignment:ita_monarchy_rebels/assignment:movement_evaluation/assignment:modifier/assignment:controlled_by=text:REB": 1,
          "assignment:ita_monarchy_rebels/assignment:movement_evaluation/assignment:modifier/assignment:factor=number:0.001": 1,
          "assignment:ita_monarchy_rebels/assignment:movement_evaluation/assignment:modifier/assignment:factor=number:0.1": 1,
          "assignment:ita_monarchy_rebels/assignment:movement_evaluation/assignment:modifier/assignment:factor=number:1.5": 3,
          "assignment:ita_monarchy_rebels/assignment:movement_evaluation/assignment:modifier/assignment:units_in_province=number:1": 1,
          "assignment:ita_monarchy_rebels/assignment:movement_evaluation/assignment:modifier/assignment:unrest=number:2": 1,
          "assignment:ita_monarchy_rebels/assignment:movement_evaluation/assignment:modifier/assignment:unrest=number:4": 1,
          "assignment:ita_monarchy_rebels/assignment:movement_evaluation/assignment:modifier/assignment:unrest=number:6": 1,
          "assignment:ita_monarchy_rebels/assignment:reinforcing=bool:yes": 1,
          "assignment:ita_monarchy_rebels/assignment:resilient=bool:yes": 1,
          "assignment:ita_monarchy_rebels/assignment:siege_won_effect/assignment:set_province_flag=text:ita_monarchy_rebellion_3": 1,
          "assignment:ita_monarchy_rebels/assignment:siege_won_trigger/assignment:region=text:italy_region": 1,
          "assignment:ita_monarchy_rebels/assignment:smart=bool:yes": 1,
          "assignment:ita_monarchy_rebels/assignment:spawn_chance/assignment:factor=number:0": 1,
          "assignment:ita_monarchy_rebels/assignment:unit_transfer=bool:yes": 1,
          "assignment:ita_monarchy_rebels/assignment:will_relocate=bool:yes": 1,
          "assignment:ita_republican_rebels/assignment:area=text:nation": 1,
          "assignment:ita_republican_rebels/assignment:artillery=number:0.1": 1,
          "assignment:ita_republican_rebels/assignment:can_enforce_trigger/assignment:always=bool:yes": 1,
          "assignment:ita_republican_rebels/assignment:can_negotiate_trigger/assignment:always=bool:no": 1,
          "assignment:ita_republican_rebels/assignment:cavalry=number:0.4": 1,
          "assignment:ita_republican_rebels/assignment:color/item=number:180": 1,
          "assignment:ita_republican_rebels/assignment:color/item=number:25": 2,
          "assignment:ita_republican_rebels/assignment:defect_delay=number:60": 1,
          "assignment:ita_republican_rebels/assignment:defection=text:none": 1,
          "assignment:ita_republican_rebels/assignment:demands_description=text:ita_republican_rebels_demand": 1,
          "assignment:ita_republican_rebels/assignment:demands_enforced_effect/assignment:add_government_reform=text:constitutional_republic_reform": 1,
          "assignment:ita_republican_rebels/assignment:demands_enforced_effect/assignment:add_prestige=number:-10": 1,
          "assignment:ita_republican_rebels/assignment:demands_enforced_effect/assignment:hidden_effect/assignment:clr_country_flag=text:ita_republican_matter": 1,
          "assignment:ita_republican_rebels/assignment:demands_enforced_effect/assignment:hidden_effect/assignment:set_country_flag=text:ita_republican_matter_subversed": 1,
          "assignment:ita_republican_rebels/assignment:demands_enforced_effect/assignment:if/assignment:change_government=text:republic": 1,
          "assignment:ita_republican_rebels/assignment:demands_enforced_effect/assignment:if/assignment:limit/assignment:NOT/assignment:government=text:republic": 1,
          "assignment:ita_republican_rebels/assignment:general=bool:yes": 1,
          "assignment:ita_republican_rebels/assignment:gfx_type=text:culture_province": 1,
          "assignment:ita_republican_rebels/assignment:government=text:any": 1,
          "assignment:ita_republican_rebels/assignment:handle_action_build_core=bool:yes": 1,
          "assignment:ita_republican_rebels/assignment:handle_action_change_culture=bool:yes": 1,
          "assignment:ita_republican_rebels/assignment:handle_action_negotiate=bool:yes": 1,
          "assignment:ita_republican_rebels/assignment:handle_action_send_missionary=bool:yes": 1,
          "assignment:ita_republican_rebels/assignment:handle_action_stability=bool:yes": 1,
          "assignment:ita_republican_rebels/assignment:independence=text:none": 1,
          "assignment:ita_republican_rebels/assignment:infantry=number:0.5": 1,
          "assignment:ita_republican_rebels/assignment:morale=number:1.1": 1,
          "assignment:ita_republican_rebels/assignment:movement_evaluation/assignment:factor=number:1": 1,
          "assignment:ita_republican_rebels/assignment:movement_evaluation/assignment:modifier/assignment:controlled_by=text:REB": 1,
          "assignment:ita_republican_rebels/assignment:movement_evaluation/assignment:modifier/assignment:factor=number:0.001": 1,
          "assignment:ita_republican_rebels/assignment:movement_evaluation/assignment:modifier/assignment:factor=number:0.1": 1,
          "assignment:ita_republican_rebels/assignment:movement_evaluation/assignment:modifier/assignment:factor=number:1.5": 3,
          "assignment:ita_republican_rebels/assignment:movement_evaluation/assignment:modifier/assignment:units_in_province=number:1": 1,
          "assignment:ita_republican_rebels/assignment:movement_evaluation/assignment:modifier/assignment:unrest=number:2": 1,
          "assignment:ita_republican_rebels/assignment:movement_evaluation/assignment:modifier/assignment:unrest=number:4": 1,
          "assignment:ita_republican_rebels/assignment:movement_evaluation/assignment:modifier/assignment:unrest=number:6": 1,
          "assignment:ita_republican_rebels/assignment:reinforcing=bool:yes": 1,
          "assignment:ita_republican_rebels/assignment:resilient=bool:yes": 1,
          "assignment:ita_republican_rebels/assignment:siege_won_effect/assignment:set_province_flag=text:ita_republican_rebellion_3": 1,
          "assignment:ita_republican_rebels/assignment:siege_won_trigger/assignment:region=text:italy_region": 1,
          "assignment:ita_republican_rebels/assignment:smart=bool:yes": 1,
          "assignment:ita_republican_rebels/assignment:spawn_chance/assignment:factor=number:0": 1,
          "assignment:ita_republican_rebels/assignment:unit_transfer=bool:yes": 1,
          "assignment:ita_republican_rebels/assignment:will_relocate=bool:yes": 1
        },
        "right_only": {}
      },
      "conflicts": [],
      "scalar_reductions": [],
      "diagnostics": [],
      "timings": {
        "view_ms": 23,
        "merge_ms": 76,
        "comparison_ms": 17,
        "copy_through_definitions": 4,
        "structured_definitions": 13,
        "comparison_reused_definitions": 56,
        "comparison_normalized_definitions": 7,
        "matcher_ns": 14937791,
        "pcs_ns": 8207131,
        "policy_ns": 49452
      }
    },
    {
      "case_id": "3630876155",
      "snapshot_id": "d60369eb6a10122a1478df23c06031a84858075f09db11574e8d29cc1a260f5c",
      "relative_path": "common/scripted_triggers/zzz_foch_scripted_triggers.txt",
      "module_prefix": "common/scripted_triggers",
      "content_family": "common/scripted_triggers",
      "source_mod_ids": [
        "2164202838",
        "2185445645"
      ],
      "legacy_verdict": "diverges_ast",
      "legacy_accepted": false,
      "status": "accepted_equivalent",
      "publishable": true,
      "policies": {
        "merge_key_source": "assignment_key",
        "nested_merge_key_source": "assignment_key",
        "scalar": "conflict",
        "list": "union",
        "one_sided_removal": "remove",
        "block": "recursive",
        "boolean": "and",
        "block_patch": "boolean_or",
        "named_container": "conflict",
        "edit_wins_over_remove": false
      },
      "view_content_ids": {
        "base": "40c4fac70c9c91f518b8f9d8a3b6e7a0e6f37ac17280bb1dc7fd156c9ca477dd",
        "left": "3dd93c4ee4349fd2fae8c4059c10ea5f9e813cc9902519fb9761f3f349e032d4",
        "right": "0cd0dbbd792bb6fb16e2ac9448c63c49b9782d8df3fa013af905bc6751e8a6f7",
        "human": "e2400c67782e8337b67f47da9a09a4eb3e558c556dcfe70da6cf0bfbb9fac8d9"
      },
      "candidate_semantic_content_id": "397d68b83893e0f486fabe45eecdedf6a52c44766e839472d4295df05a5f46d2",
      "base_definitions": 2507,
      "active_definitions": 519,
      "missing_top_level_keys": [],
      "extra_top_level_keys": [],
      "semantic_diff_from_human": {
        "left_atoms": 24931,
        "right_atoms": 24931,
        "shared_atoms": 24931,
        "left_only": {},
        "right_only": {}
      },
      "conflicts": [],
      "scalar_reductions": [],
      "diagnostics": [],
      "timings": {
        "view_ms": 59,
        "merge_ms": 544,
        "comparison_ms": 738,
        "copy_through_definitions": 473,
        "structured_definitions": 46,
        "comparison_reused_definitions": 3013,
        "comparison_normalized_definitions": 12,
        "matcher_ns": 920498,
        "pcs_ns": 11294449,
        "policy_ns": 62011
      }
    },
    {
      "case_id": "3630904821",
      "snapshot_id": "695b4ed11d04270342f5cb007ebd14001513bd91e3187434a6531e8f76ab7d7c",
      "relative_path": "common/scripted_triggers/zzz_foch_scripted_triggers.txt",
      "module_prefix": "common/scripted_triggers",
      "content_family": "common/scripted_triggers",
      "source_mod_ids": [
        "2164202838",
        "1352521684"
      ],
      "legacy_verdict": "diverges_ast",
      "legacy_accepted": false,
      "status": "accepted_equivalent",
      "publishable": true,
      "policies": {
        "merge_key_source": "assignment_key",
        "nested_merge_key_source": "assignment_key",
        "scalar": "conflict",
        "list": "union",
        "one_sided_removal": "remove",
        "block": "recursive",
        "boolean": "and",
        "block_patch": "boolean_or",
        "named_container": "conflict",
        "edit_wins_over_remove": false
      },
      "view_content_ids": {
        "base": "40c4fac70c9c91f518b8f9d8a3b6e7a0e6f37ac17280bb1dc7fd156c9ca477dd",
        "left": "3dd93c4ee4349fd2fae8c4059c10ea5f9e813cc9902519fb9761f3f349e032d4",
        "right": "f8640e0c89fe59074caabc4bd88dd444ee2a39d50b6a8c660de494b9076d1940",
        "human": "9d76d6cc4d15ff3f8821a82c43d06d65b3e62e7082f11daab5cf1606d3ed4241"
      },
      "candidate_semantic_content_id": "aa907cb5712bfa6d971a3372119909d9f24e4f9a5511363a80f8f6f7c1f8b3f8",
      "base_definitions": 2507,
      "active_definitions": 582,
      "missing_top_level_keys": [],
      "extra_top_level_keys": [],
      "semantic_diff_from_human": {
        "left_atoms": 25878,
        "right_atoms": 25878,
        "shared_atoms": 25878,
        "left_only": {},
        "right_only": {}
      },
      "conflicts": [],
      "scalar_reductions": [],
      "diagnostics": [],
      "timings": {
        "view_ms": 10,
        "merge_ms": 577,
        "comparison_ms": 786,
        "copy_through_definitions": 533,
        "structured_definitions": 49,
        "comparison_reused_definitions": 3075,
        "comparison_normalized_definitions": 13,
        "matcher_ns": 1323253,
        "pcs_ns": 17969693,
        "policy_ns": 98437
      }
    },
    {
      "case_id": "3630934157",
      "snapshot_id": "ebdf8ea89e7fa5edb103708cdab2ce02dca53af16642d4aa1f5e577781033e30",
      "relative_path": "common/religions/zzz_foch_religions.txt",
      "module_prefix": "common/religions",
      "content_family": "common/religions",
      "source_mod_ids": [
        "3342969370",
        "2164202838"
      ],
      "legacy_verdict": "accepted_equivalent",
      "legacy_accepted": true,
      "status": "accepted_equivalent",
      "publishable": true,
      "policies": {
        "merge_key_source": "assignment_key",
        "nested_merge_key_source": "assignment_key",
        "scalar": "last_writer",
        "list": "replace",
        "one_sided_removal": "remove",
        "block": "recursive",
        "boolean": "and",
        "block_patch": "recurse",
        "named_container": "conflict",
        "edit_wins_over_remove": false
      },
      "view_content_ids": {
        "base": "8ecb999d611573c320e7b8e41b4a74c38fc6b4e5223b7fbe2b25a6cd1b0b3dab",
        "left": "588f49ef0ab32e5b0f275a5964d6a1e91abd18880c2af95ff373119d2e99484d",
        "right": "07638ca8983644f6447358decb55941e7f61c31f16765e56eb6f44003a60a0e6",
        "human": "ab1b8569cd6dc7af64ad99e1c510fe76da6344fdd41434582627f7dc5f35fc88"
      },
      "candidate_semantic_content_id": "43d691bf29ba649afc26908a4b0d5c3cfac25e38f6e4f0b90d05c158ddf5e01f",
      "base_definitions": 7,
      "active_definitions": 5,
      "missing_top_level_keys": [],
      "extra_top_level_keys": [],
      "semantic_diff_from_human": {
        "left_atoms": 1682,
        "right_atoms": 1682,
        "shared_atoms": 1682,
        "left_only": {},
        "right_only": {}
      },
      "conflicts": [],
      "scalar_reductions": [],
      "diagnostics": [],
      "timings": {
        "view_ms": 6,
        "merge_ms": 64,
        "comparison_ms": 16,
        "copy_through_definitions": 2,
        "structured_definitions": 3,
        "comparison_reused_definitions": 4,
        "comparison_normalized_definitions": 3,
        "matcher_ns": 30465875,
        "pcs_ns": 8705680,
        "policy_ns": 58403
      }
    },
    {
      "case_id": "3634824708",
      "snapshot_id": "54fb216188ec4267c3006b2b05b8c994ba75961a7337839a05a9f23272d62d0c",
      "relative_path": "common/buildings/zzz_foch_buildings.txt",
      "module_prefix": "common/buildings",
      "content_family": "common/buildings",
      "source_mod_ids": [
        "2164202838",
        "1770950522"
      ],
      "legacy_verdict": "diverges_ast",
      "legacy_accepted": false,
      "status": "manual_resolution_required",
      "publishable": false,
      "policies": {
        "merge_key_source": "assignment_key",
        "nested_merge_key_source": "assignment_key",
        "scalar": "last_writer",
        "list": "replace",
        "one_sided_removal": "preserve_if_parent_survives",
        "block": "recursive",
        "boolean": "and",
        "block_patch": "recurse",
        "named_container": "conflict",
        "edit_wins_over_remove": false
      },
      "view_content_ids": {
        "base": "41453a4348e3ff5d2179134b53df3000a11697fea5afa8a53d83e76c49dbd559",
        "left": "ee312a95023ef86476e2b9242569de2b7ae77a91f98967f670cd0c1d8504c204",
        "right": "c8c0d9b846b31d7e21bb56521e2a7e8577049b892040ccd56d27ae5c8f3e0d9a",
        "human": "03ea84f67dc803528ae7fbf675a0c3e9e1d2c0980e2a0eed1bf539fdb89e367f"
      },
      "candidate_semantic_content_id": "bcf3e790532baae6df0fdc39b8425a3d2bf4e544d59161ccc9c77085e32454b0",
      "base_definitions": 47,
      "active_definitions": 65,
      "missing_top_level_keys": [],
      "extra_top_level_keys": [],
      "semantic_diff_from_human": {
        "left_atoms": 2351,
        "right_atoms": 2327,
        "shared_atoms": 2326,
        "left_only": {
          "assignment:courthouse/assignment:ai_will_do/assignment:modifier/assignment:FROM/assignment:NOT/assignment:treasury=number:200": 1,
          "assignment:courthouse/assignment:ai_will_do/assignment:modifier/assignment:FROM/assignment:governing_capacity_percentage=number:0.8": 1,
          "assignment:courthouse/assignment:ai_will_do/assignment:modifier/assignment:FROM/assignment:governing_capacity_percentage=number:1": 1,
          "assignment:courthouse/assignment:ai_will_do/assignment:modifier/assignment:FROM/assignment:is_in_deficit=bool:yes": 1,
          "assignment:courthouse/assignment:ai_will_do/assignment:modifier/assignment:FROM/assignment:num_of_loans=number:1": 1,
          "assignment:courthouse/assignment:ai_will_do/assignment:modifier/assignment:FROM/assignment:num_of_loans=number:2": 1,
          "assignment:courthouse/assignment:ai_will_do/assignment:modifier/assignment:FROM/assignment:num_of_loans=number:3": 1,
          "assignment:courthouse/assignment:ai_will_do/assignment:modifier/assignment:FROM/assignment:treasury=number:300": 1,
          "assignment:courthouse/assignment:ai_will_do/assignment:modifier/assignment:development=number:10": 1,
          "assignment:courthouse/assignment:ai_will_do/assignment:modifier/assignment:development=number:20": 1,
          "assignment:courthouse/assignment:ai_will_do/assignment:modifier/assignment:development=number:30": 1,
          "assignment:courthouse/assignment:ai_will_do/assignment:modifier/assignment:factor=number:0": 1,
          "assignment:courthouse/assignment:ai_will_do/assignment:modifier/assignment:factor=number:0.25": 1,
          "assignment:courthouse/assignment:ai_will_do/assignment:modifier/assignment:factor=number:0.5": 2,
          "assignment:courthouse/assignment:ai_will_do/assignment:modifier/assignment:factor=number:0.75": 1,
          "assignment:courthouse/assignment:ai_will_do/assignment:modifier/assignment:factor=number:1.25": 4,
          "assignment:courthouse/assignment:ai_will_do/assignment:modifier/assignment:factor=number:2": 1,
          "assignment:courthouse/assignment:ai_will_do/assignment:modifier/assignment:factor=number:3": 1,
          "assignment:shipyard/assignment:ai_will_do/assignment:modifier/assignment:FROM/assignment:num_of_loans=number:1": 1,
          "assignment:shipyard/assignment:ai_will_do/assignment:modifier/assignment:factor=number:0": 1,
          "assignment:tradecompany/assignment:manufactory/item=text:cloves": 1
        },
        "right_only": {
          "assignment:shipyard/assignment:ai_will_do/assignment:modifier/assignment:factor=number:1.5": 1
        }
      },
      "conflicts": [
        {
          "kind": "ambiguous_match",
          "detail": "definition `courthouse`: node 62 (kind=`clausewitz.assignment:modifier` value=`modifier` anchor=`clausewitz.assignment.key:modifier`) has 2 equally ranked candidates at score 750000: kind=`clausewitz.assignment:modifier` value=`modifier` anchor=`clausewitz.assignment.key:modifier`; kind=`clausewitz.assignment:modifier` value=`modifier` anchor=`clausewitz.assignment.key:modifier`"
        },
        {
          "kind": "ambiguous_match",
          "detail": "definition `courthouse`: node 70 (kind=`clausewitz.assignment:modifier` value=`modifier` anchor=`clausewitz.assignment.key:modifier`) has 3 equally ranked candidates at score 750000: kind=`clausewitz.assignment:modifier` value=`modifier` anchor=`clausewitz.assignment.key:modifier`; kind=`clausewitz.assignment:modifier` value=`modifier` anchor=`clausewitz.assignment.key:modifier`; kind=`clausewitz.assignment:modifier` value=`modifier` anchor=`clausewitz.assignment.key:modifier`"
        },
        {
          "kind": "ambiguous_match",
          "detail": "definition `courthouse`: node 86 (kind=`clausewitz.assignment:modifier` value=`modifier` anchor=`clausewitz.assignment.key:modifier`) has 1 equally ranked candidates at score 875000: kind=`clausewitz.assignment:modifier` value=`modifier` anchor=`clausewitz.assignment.key:modifier`"
        },
        {
          "kind": "ambiguous_match",
          "detail": "definition `courthouse`: node 94 (kind=`clausewitz.assignment:modifier` value=`modifier` anchor=`clausewitz.assignment.key:modifier`) has 1 equally ranked candidates at score 750000: kind=`clausewitz.assignment:modifier` value=`modifier` anchor=`clausewitz.assignment.key:modifier`"
        },
        {
          "kind": "ambiguous_match",
          "detail": "definition `courthouse`: node 102 (kind=`clausewitz.assignment:modifier` value=`modifier` anchor=`clausewitz.assignment.key:modifier`) has 1 equally ranked candidates at score 875000: kind=`clausewitz.assignment:modifier` value=`modifier` anchor=`clausewitz.assignment.key:modifier`"
        },
        {
          "kind": "ambiguous_match",
          "detail": "definition `courthouse`: node 110 (kind=`clausewitz.assignment:modifier` value=`modifier` anchor=`clausewitz.assignment.key:modifier`) has 5 equally ranked candidates at score 625000: kind=`clausewitz.assignment:modifier` value=`modifier` anchor=`clausewitz.assignment.key:modifier`; kind=`clausewitz.assignment:modifier` value=`modifier` anchor=`clausewitz.assignment.key:modifier`; kind=`clausewitz.assignment:modifier` value=`modifier` anchor=`clausewitz.assignment.key:modifier`; kind=`clausewitz.assignment:modifier` value=`modifier` anchor=`clausewitz.assignment.key:modifier`; kind=`clausewitz.assignment:modifier` value=`modifier` anchor=`clausewitz.assignment.key:modifier`"
        },
        {
          "kind": "ambiguous_match",
          "detail": "definition `courthouse`: node 136 (kind=`clausewitz.assignment:modifier` value=`modifier` anchor=`clausewitz.assignment.key:modifier`) has 2 equally ranked candidates at score 666666: kind=`clausewitz.assignment:modifier` value=`modifier` anchor=`clausewitz.assignment.key:modifier`; kind=`clausewitz.assignment:modifier` value=`modifier` anchor=`clausewitz.assignment.key:modifier`"
        },
        {
          "kind": "ambiguous_match",
          "detail": "definition `courthouse`: node 146 (kind=`clausewitz.assignment:modifier` value=`modifier` anchor=`clausewitz.assignment.key:modifier`) has 2 equally ranked candidates at score 750000: kind=`clausewitz.assignment:modifier` value=`modifier` anchor=`clausewitz.assignment.key:modifier`; kind=`clausewitz.assignment:modifier` value=`modifier` anchor=`clausewitz.assignment.key:modifier`"
        },
        {
          "kind": "ambiguous_match",
          "detail": "definition `courthouse`: node 94 (kind=`clausewitz.assignment:modifier` value=`modifier` anchor=`clausewitz.assignment.key:modifier`) has 2 equally ranked candidates at score 750000: kind=`clausewitz.assignment:modifier` value=`modifier` anchor=`clausewitz.assignment.key:modifier`; kind=`clausewitz.assignment:modifier` value=`modifier` anchor=`clausewitz.assignment.key:modifier`"
        },
        {
          "kind": "ambiguous_match",
          "detail": "definition `courthouse`: node 102 (kind=`clausewitz.assignment:modifier` value=`modifier` anchor=`clausewitz.assignment.key:modifier`) has 3 equally ranked candidates at score 750000: kind=`clausewitz.assignment:modifier` value=`modifier` anchor=`clausewitz.assignment.key:modifier`; kind=`clausewitz.assignment:modifier` value=`modifier` anchor=`clausewitz.assignment.key:modifier`; kind=`clausewitz.assignment:modifier` value=`modifier` anchor=`clausewitz.assignment.key:modifier`"
        },
        {
          "kind": "ambiguous_match",
          "detail": "definition `courthouse`: node 118 (kind=`clausewitz.assignment:modifier` value=`modifier` anchor=`clausewitz.assignment.key:modifier`) has 1 equally ranked candidates at score 875000: kind=`clausewitz.assignment:modifier` value=`modifier` anchor=`clausewitz.assignment.key:modifier`"
        },
        {
          "kind": "ambiguous_match",
          "detail": "definition `courthouse`: node 126 (kind=`clausewitz.assignment:modifier` value=`modifier` anchor=`clausewitz.assignment.key:modifier`) has 1 equally ranked candidates at score 750000: kind=`clausewitz.assignment:modifier` value=`modifier` anchor=`clausewitz.assignment.key:modifier`"
        },
        {
          "kind": "ambiguous_match",
          "detail": "definition `courthouse`: node 134 (kind=`clausewitz.assignment:modifier` value=`modifier` anchor=`clausewitz.assignment.key:modifier`) has 1 equally ranked candidates at score 875000: kind=`clausewitz.assignment:modifier` value=`modifier` anchor=`clausewitz.assignment.key:modifier`"
        },
        {
          "kind": "ambiguous_match",
          "detail": "definition `courthouse`: node 142 (kind=`clausewitz.assignment:modifier` value=`modifier` anchor=`clausewitz.assignment.key:modifier`) has 5 equally ranked candidates at score 625000: kind=`clausewitz.assignment:modifier` value=`modifier` anchor=`clausewitz.assignment.key:modifier`; kind=`clausewitz.assignment:modifier` value=`modifier` anchor=`clausewitz.assignment.key:modifier`; kind=`clausewitz.assignment:modifier` value=`modifier` anchor=`clausewitz.assignment.key:modifier`; kind=`clausewitz.assignment:modifier` value=`modifier` anchor=`clausewitz.assignment.key:modifier`; kind=`clausewitz.assignment:modifier` value=`modifier` anchor=`clausewitz.assignment.key:modifier`"
        },
        {
          "kind": "ambiguous_match",
          "detail": "definition `courthouse`: node 168 (kind=`clausewitz.assignment:modifier` value=`modifier` anchor=`clausewitz.assignment.key:modifier`) has 2 equally ranked candidates at score 666666: kind=`clausewitz.assignment:modifier` value=`modifier` anchor=`clausewitz.assignment.key:modifier`; kind=`clausewitz.assignment:modifier` value=`modifier` anchor=`clausewitz.assignment.key:modifier`"
        },
        {
          "kind": "ambiguous_match",
          "detail": "definition `courthouse`: node 178 (kind=`clausewitz.assignment:modifier` value=`modifier` anchor=`clausewitz.assignment.key:modifier`) has 2 equally ranked candidates at score 750000: kind=`clausewitz.assignment:modifier` value=`modifier` anchor=`clausewitz.assignment.key:modifier`; kind=`clausewitz.assignment:modifier` value=`modifier` anchor=`clausewitz.assignment.key:modifier`"
        }
      ],
      "scalar_reductions": [],
      "diagnostics": [],
      "timings": {
        "view_ms": 9,
        "merge_ms": 60,
        "comparison_ms": 17,
        "copy_through_definitions": 0,
        "structured_definitions": 65,
        "comparison_reused_definitions": 54,
        "comparison_normalized_definitions": 32,
        "matcher_ns": 13711247,
        "pcs_ns": 12984591,
        "policy_ns": 93034
      }
    },
    {
      "case_id": "3634824708",
      "snapshot_id": "54fb216188ec4267c3006b2b05b8c994ba75961a7337839a05a9f23272d62d0c",
      "relative_path": "common/institutions/zzz_foch_institutions.txt",
      "module_prefix": "common/institutions",
      "content_family": "common/institutions",
      "source_mod_ids": [
        "2164202838",
        "1770950522"
      ],
      "legacy_verdict": "diverges_ast",
      "legacy_accepted": false,
      "status": "accepted_equivalent",
      "publishable": true,
      "policies": {
        "merge_key_source": "assignment_key",
        "nested_merge_key_source": "assignment_key",
        "scalar": "sum",
        "list": "union",
        "one_sided_removal": "preserve_boolean_alternatives",
        "block": "recursive",
        "boolean": "and",
        "block_patch": "recurse",
        "named_container": "conflict",
        "edit_wins_over_remove": false
      },
      "view_content_ids": {
        "base": "2d9718feb070c841a52a3492fd04f59a4c07a6fd18bb84f2229b535befcb39d7",
        "left": "e2f95a3a48a4a6f58eaf64a7b5a694b2f1accb5a0c64d2304f33bf178637f2e8",
        "right": "64b6956954a4f21664e198f78d06d29a09a6137f0e34afdb2cc54662d06042b6",
        "human": "105ef150baa307e680be3c9021d876f14121cc2a0102d08f5e90152ff01b669f"
      },
      "candidate_semantic_content_id": "105ef150baa307e680be3c9021d876f14121cc2a0102d08f5e90152ff01b669f",
      "base_definitions": 8,
      "active_definitions": 3,
      "missing_top_level_keys": [],
      "extra_top_level_keys": [],
      "semantic_diff_from_human": {
        "left_atoms": 1548,
        "right_atoms": 1548,
        "shared_atoms": 1548,
        "left_only": {},
        "right_only": {}
      },
      "conflicts": [],
      "scalar_reductions": [],
      "diagnostics": [],
      "timings": {
        "view_ms": 6,
        "merge_ms": 43,
        "comparison_ms": 9,
        "copy_through_definitions": 0,
        "structured_definitions": 3,
        "comparison_reused_definitions": 5,
        "comparison_normalized_definitions": 3,
        "matcher_ns": 19250292,
        "pcs_ns": 5444733,
        "policy_ns": 35101
      }
    },
    {
      "case_id": "3634824708",
      "snapshot_id": "54fb216188ec4267c3006b2b05b8c994ba75961a7337839a05a9f23272d62d0c",
      "relative_path": "common/tradegoods/zzz_foch_tradegoods.txt",
      "module_prefix": "common/tradegoods",
      "content_family": "common/tradegoods",
      "source_mod_ids": [
        "2164202838",
        "1770950522"
      ],
      "legacy_verdict": "diverges_ast",
      "legacy_accepted": false,
      "status": "semantic_mismatch",
      "publishable": false,
      "policies": {
        "merge_key_source": "assignment_key",
        "nested_merge_key_source": "assignment_key",
        "scalar": "conflict",
        "list": "replace",
        "one_sided_removal": "preserve_if_parent_survives",
        "block": "recursive",
        "boolean": "and",
        "block_patch": "recurse",
        "named_container": "conflict",
        "edit_wins_over_remove": false
      },
      "view_content_ids": {
        "base": "838b592983f658ad7b5277e1d4feeac3e819bc3a39538601f772438f392da42c",
        "left": "da018be295fa6167eb8f0f3612b11b809bfba0ff67791aa8cc24e120a96d8682",
        "right": "7a17c4d09622e3d9dd0af13b24cfa347199557b04bd5f53931be7a7a153f664b",
        "human": "3001c05361663251421d7a30c2d45237cdcf44250def03686a1c93bcb48bdb98"
      },
      "candidate_semantic_content_id": "c3147bd9ddcd9edbbd8edf80e46490ab1038fff988c3331ab70284d9ec15add3",
      "base_definitions": 32,
      "active_definitions": 91,
      "missing_top_level_keys": [],
      "extra_top_level_keys": [],
      "semantic_diff_from_human": {
        "left_atoms": 2951,
        "right_atoms": 2943,
        "shared_atoms": 2943,
        "left_only": {
          "assignment:cloves/assignment:chance/assignment:modifier/assignment:NOT/assignment:OR/assignment:area=text:molluca_area": 1,
          "assignment:cloves/assignment:chance/assignment:modifier/assignment:NOT/assignment:OR/assignment:area=text:spice_islands_area": 1,
          "assignment:coal/assignment:trigger/assignment:else_if/assignment:limit/assignment:owner/assignment:has_country_flag=text:ENG_early_inno_coal": 1,
          "assignment:coal/assignment:trigger/assignment:else_if/assignment:owner/assignment:adm_tech=number:22": 1,
          "assignment:coal/assignment:trigger/assignment:else_if/assignment:owner/assignment:innovativeness=number:80": 1,
          "assignment:coal/assignment:trigger/assignment:else_if/assignment:provincial_institution_progress/assignment:value=number:100": 1,
          "assignment:coal/assignment:trigger/assignment:else_if/assignment:provincial_institution_progress/assignment:which=text:manufactories": 1,
          "assignment:dyes/assignment:modifier/assignment:heir_chance=number:0.33": 1
        },
        "right_only": {}
      },
      "conflicts": [],
      "scalar_reductions": [
        {
          "path": [
            "cloves",
            "province",
            "province_trade_power_modifier"
          ],
          "inputs": [
            [
              1,
              "0.2"
            ],
            [
              2,
              "0.1"
            ]
          ],
          "output": "0.15"
        }
      ],
      "diagnostics": [],
      "timings": {
        "view_ms": 8,
        "merge_ms": 80,
        "comparison_ms": 24,
        "copy_through_definitions": 0,
        "structured_definitions": 91,
        "comparison_reused_definitions": 44,
        "comparison_normalized_definitions": 48,
        "matcher_ns": 21456712,
        "pcs_ns": 18302461,
        "policy_ns": 137205
      }
    },
    {
      "case_id": "3634829839",
      "snapshot_id": "24048fe131d8365e61b3d70172e57d57f6a38ffb000f19a30ee35c20935a5803",
      "relative_path": "common/ages/zzz_foch_ages.txt",
      "module_prefix": "common/ages",
      "content_family": "common/ages",
      "source_mod_ids": [
        "2172666098",
        "2164202838"
      ],
      "legacy_verdict": "diverges_ast",
      "legacy_accepted": false,
      "status": "semantic_mismatch",
      "publishable": false,
      "policies": {
        "merge_key_source": "assignment_key",
        "nested_merge_key_source": "assignment_key",
        "scalar": "conflict",
        "list": "ordered_union",
        "one_sided_removal": "remove",
        "block": "recursive",
        "boolean": "and",
        "block_patch": "recurse",
        "named_container": "conflict",
        "edit_wins_over_remove": false
      },
      "view_content_ids": {
        "base": "174afd58f652268c6072af9e735b33cd7f44da19f0c26f07cb66873a4fe72679",
        "left": "f35b91b76dc80f6e5a8405d49e753c4f8c2c5507b8c169a7bdeb664929840107",
        "right": "c88984f064eec46d5dbe5c19e64b9ef18671b538a34ed794b83044644449e446",
        "human": "a67508f647f071cbf84989d47cf5d93f46afa7d2a318137b507b753725c7cb97"
      },
      "candidate_semantic_content_id": "a562dd848e850e72d9010482f3248371d0f0a0316acf40fb21475ddd4576c22d",
      "base_definitions": 4,
      "active_definitions": 4,
      "missing_top_level_keys": [],
      "extra_top_level_keys": [],
      "semantic_diff_from_human": {
        "left_atoms": 608,
        "right_atoms": 607,
        "shared_atoms": 606,
        "left_only": {
          "assignment:age_of_discovery/assignment:abilities/assignment:ab_portugal_colonial_growth/assignment:modifier/assignment:global_colonial_growth=number:35": 1,
          "assignment:age_of_reformation/assignment:objectives/assignment:obj_colonial_empire/assignment:colony=number:5": 1
        },
        "right_only": {
          "assignment:age_of_discovery/assignment:abilities/assignment:ab_portugal_colonial_growth/assignment:modifier/assignment:global_colonial_growth=number:50": 1
        }
      },
      "conflicts": [],
      "scalar_reductions": [],
      "diagnostics": [],
      "timings": {
        "view_ms": 6,
        "merge_ms": 24,
        "comparison_ms": 7,
        "copy_through_definitions": 1,
        "structured_definitions": 3,
        "comparison_reused_definitions": 1,
        "comparison_normalized_definitions": 3,
        "matcher_ns": 9120583,
        "pcs_ns": 4151369,
        "policy_ns": 25715
      }
    },
    {
      "case_id": "3634829839",
      "snapshot_id": "24048fe131d8365e61b3d70172e57d57f6a38ffb000f19a30ee35c20935a5803",
      "relative_path": "common/scripted_triggers/zzz_foch_scripted_triggers.txt",
      "module_prefix": "common/scripted_triggers",
      "content_family": "common/scripted_triggers",
      "source_mod_ids": [
        "2172666098",
        "2164202838"
      ],
      "legacy_verdict": "diverges_ast",
      "legacy_accepted": false,
      "status": "accepted_equivalent",
      "publishable": true,
      "policies": {
        "merge_key_source": "assignment_key",
        "nested_merge_key_source": "assignment_key",
        "scalar": "conflict",
        "list": "union",
        "one_sided_removal": "remove",
        "block": "recursive",
        "boolean": "and",
        "block_patch": "boolean_or",
        "named_container": "conflict",
        "edit_wins_over_remove": false
      },
      "view_content_ids": {
        "base": "40c4fac70c9c91f518b8f9d8a3b6e7a0e6f37ac17280bb1dc7fd156c9ca477dd",
        "left": "3ea14897ca40c9a8f56b4eb295af7757db6589a478fd30381e4e4032c24b6dfa",
        "right": "3dd93c4ee4349fd2fae8c4059c10ea5f9e813cc9902519fb9761f3f349e032d4",
        "human": "57e90b2c02cd8e89c5451367434472358683f8f935eba338dcefcaa829c63cc3"
      },
      "candidate_semantic_content_id": "864caecf77bb501d911a2b5976ef3082c6880d043d9865bd3ee132f023e08730",
      "base_definitions": 2507,
      "active_definitions": 534,
      "missing_top_level_keys": [],
      "extra_top_level_keys": [],
      "semantic_diff_from_human": {
        "left_atoms": 25057,
        "right_atoms": 25057,
        "shared_atoms": 25057,
        "left_only": {},
        "right_only": {}
      },
      "conflicts": [],
      "scalar_reductions": [],
      "diagnostics": [],
      "timings": {
        "view_ms": 11,
        "merge_ms": 545,
        "comparison_ms": 747,
        "copy_through_definitions": 471,
        "structured_definitions": 63,
        "comparison_reused_definitions": 3021,
        "comparison_normalized_definitions": 19,
        "matcher_ns": 1117247,
        "pcs_ns": 13530563,
        "policy_ns": 75688
      }
    },
    {
      "case_id": "3635635014",
      "snapshot_id": "b1f12d633dd249e644a0205708e8c23898d990eb8eea8d43134ff78188ef61f7",
      "relative_path": "common/governments/zzz_foch_governments.txt",
      "module_prefix": "common/governments",
      "content_family": "common/governments",
      "source_mod_ids": [
        "2164202838",
        "1596815683"
      ],
      "legacy_verdict": "diverges_ast",
      "legacy_accepted": false,
      "status": "semantic_mismatch",
      "publishable": false,
      "policies": {
        "merge_key_source": "assignment_key",
        "nested_merge_key_source": "assignment_key",
        "scalar": "conflict",
        "list": "ordered_union",
        "one_sided_removal": "remove",
        "block": "recursive",
        "boolean": "and",
        "block_patch": "recurse",
        "named_container": "conflict",
        "edit_wins_over_remove": false
      },
      "view_content_ids": {
        "base": "bc80200a0ad4e2a1d5df32501510fc96828e78d2275372dd6f340d7032900056",
        "left": "9f143716a440c8b624ef7621ab02ba596fd3c9e5b823d52657097310a42cf6a9",
        "right": "939604cc88ad420d1ca55e29dda02d906adc8cf2eaa67c8e4138db55a9dccb78",
        "human": "6650e78f2f5dc55eec2ee770dbcc04ee7a8e878e4677ca49933c367123f9d7ff"
      },
      "candidate_semantic_content_id": "5a97f888bd2af21be92ee1dffcffef03b5608a1609071633fa4711f7d041d31f",
      "base_definitions": 6,
      "active_definitions": 5,
      "missing_top_level_keys": [],
      "extra_top_level_keys": [],
      "semantic_diff_from_human": {
        "left_atoms": 2046,
        "right_atoms": 1894,
        "shared_atoms": 1894,
        "left_only": {
          "assignment:monarchy/assignment:exclusive_reforms/item=text:ME_caliphate_feudal_theocracy": 1,
          "assignment:monarchy/assignment:exclusive_reforms/item=text:ME_caliphate_iqta": 1,
          "assignment:monarchy/assignment:exclusive_reforms/item=text:ME_enlist_the_help_of_sufi_orders": 1,
          "assignment:monarchy/assignment:exclusive_reforms/item=text:ME_enlist_the_help_of_sufi_orders_ADU": 1,
          "assignment:monarchy/assignment:exclusive_reforms/item=text:ME_ibadi_community": 1,
          "assignment:monarchy/assignment:exclusive_reforms/item=text:ME_ottoman_government": 1,
          "assignment:monarchy/assignment:exclusive_reforms/item=text:ME_tribal_federation_monarchy": 1,
          "assignment:monarchy/assignment:exclusive_reforms/item=text:khaganate": 1,
          "assignment:monarchy/assignment:legacy_government/item=text:athenian_monarchy_legacy": 1,
          "assignment:monarchy/assignment:legacy_government/item=text:crusader_kingdom_legacy": 1,
          "assignment:monarchy/assignment:legacy_government/item=text:german_kaiserreich_legacy": 1,
          "assignment:monarchy/assignment:legacy_government/item=text:khaganate_legacy": 1,
          "assignment:monarchy/assignment:legacy_government/item=text:west_slavic_legacy": 1,
          "assignment:monarchy/assignment:reform_levels/assignment:absolute_rule_vs_constitutional/assignment:reforms/item=text:tur_absolute_sultanic_power": 1,
          "assignment:monarchy/assignment:reform_levels/assignment:bureaucracy/assignment:reforms/item=text:EE_SCO_expand_imperial_court_reform": 1,
          "assignment:monarchy/assignment:reform_levels/assignment:bureaucracy/assignment:reforms/item=text:EE_decentralize_reform": 1,
          "assignment:monarchy/assignment:reform_levels/assignment:bureaucracy/assignment:reforms/item=text:EE_regional_council_reform": 1,
          "assignment:monarchy/assignment:reform_levels/assignment:bureaucracy/assignment:reforms/item=text:GAL_settling_the_terra_icognita": 1,
          "assignment:monarchy/assignment:reform_levels/assignment:bureaucracy/assignment:reforms/item=text:ara_consell_de_cent": 1,
          "assignment:monarchy/assignment:reform_levels/assignment:bureaucracy/assignment:reforms/item=text:mil_sforza_administration": 1,
          "assignment:monarchy/assignment:reform_levels/assignment:bureaucracy/assignment:reforms/item=text:tur_organized_pashas_reform": 1,
          "assignment:monarchy/assignment:reform_levels/assignment:bureaucracy/assignment:reforms/item=text:tur_reform_beylerbeys": 1,
          "assignment:monarchy/assignment:reform_levels/assignment:bureaucracy/assignment:reforms/item=text:tur_reform_eyalets": 1,
          "assignment:monarchy/assignment:reform_levels/assignment:deliberative_assembly/assignment:reforms/item=text:ME_system_of_councils": 1,
          "assignment:monarchy/assignment:reform_levels/assignment:deliberative_assembly/assignment:reforms/item=text:me_hindu_administration": 1,
          "assignment:monarchy/assignment:reform_levels/assignment:economical_matters/assignment:reforms/item=text:EE_curtail_the_burghers_reform": 1,
          "assignment:monarchy/assignment:reform_levels/assignment:economical_matters/assignment:reforms/item=text:EE_modernize_industrial_sector": 1,
          "assignment:monarchy/assignment:reform_levels/assignment:feudalism_vs_autocracy/assignment:reforms/item=text:ARA_crown_of_aragon": 1,
          "assignment:monarchy/assignment:reform_levels/assignment:feudalism_vs_autocracy/assignment:reforms/item=text:EE_Celtic_Union": 1,
          "assignment:monarchy/assignment:reform_levels/assignment:feudalism_vs_autocracy/assignment:reforms/item=text:EE_FRA_ancien_regime": 1,
          "assignment:monarchy/assignment:reform_levels/assignment:feudalism_vs_autocracy/assignment:reforms/item=text:EE_IRE_Ardi_Heireann": 1,
          "assignment:monarchy/assignment:reform_levels/assignment:feudalism_vs_autocracy/assignment:reforms/item=text:EE_IRE_Irish_Kingdom": 1,
          "assignment:monarchy/assignment:reform_levels/assignment:feudalism_vs_autocracy/assignment:reforms/item=text:EE_Minor_IRI_Gaelic_Kingship": 1,
          "assignment:monarchy/assignment:reform_levels/assignment:feudalism_vs_autocracy/assignment:reforms/item=text:EE_Minor_IRI_Gaelic_Kingship_Parliament": 1,
          "assignment:monarchy/assignment:reform_levels/assignment:feudalism_vs_autocracy/assignment:reforms/item=text:EE_synthetic_monarchy": 1,
          "assignment:monarchy/assignment:reform_levels/assignment:feudalism_vs_autocracy/assignment:reforms/item=text:EE_synthetic_monarchy_militarized": 1,
          "assignment:monarchy/assignment:reform_levels/assignment:feudalism_vs_autocracy/assignment:reforms/item=text:FRX_frankish_monarchy": 1,
          "assignment:monarchy/assignment:reform_levels/assignment:feudalism_vs_autocracy/assignment:reforms/item=text:ME_Celtic_High_Kingdom": 1,
          "assignment:monarchy/assignment:reform_levels/assignment:feudalism_vs_autocracy/assignment:reforms/item=text:ME_caliphate_reform_shia_ibadi": 1,
          "assignment:monarchy/assignment:reform_levels/assignment:feudalism_vs_autocracy/assignment:reforms/item=text:ME_caliphate_reform_sunni": 1,
          "assignment:monarchy/assignment:reform_levels/assignment:feudalism_vs_autocracy/assignment:reforms/item=text:ME_caliphate_reform_sunni_andalusia": 1,
          "assignment:monarchy/assignment:reform_levels/assignment:feudalism_vs_autocracy/assignment:reforms/item=text:ME_caliphate_reform_sunni_arabian": 1,
          "assignment:monarchy/assignment:reform_levels/assignment:feudalism_vs_autocracy/assignment:reforms/item=text:ME_ibadi_community": 1,
          "assignment:monarchy/assignment:reform_levels/assignment:feudalism_vs_autocracy/assignment:reforms/item=text:ME_ottoman_government": 1,
          "assignment:monarchy/assignment:reform_levels/assignment:feudalism_vs_autocracy/assignment:reforms/item=text:ME_tribal_federation_monarchy": 1,
          "assignment:monarchy/assignment:reform_levels/assignment:feudalism_vs_autocracy/assignment:reforms/item=text:POR_portuguese_colonial_autocracy": 1,
          "assignment:monarchy/assignment:reform_levels/assignment:feudalism_vs_autocracy/assignment:reforms/item=text:POR_portuguese_monarchy": 1,
          "assignment:monarchy/assignment:reform_levels/assignment:feudalism_vs_autocracy/assignment:reforms/item=text:RHN_autocratic_capitalism": 1,
          "assignment:monarchy/assignment:reform_levels/assignment:feudalism_vs_autocracy/assignment:reforms/item=text:UKS_angevin_monarchy_reform": 1,
          "assignment:monarchy/assignment:reform_levels/assignment:feudalism_vs_autocracy/assignment:reforms/item=text:ada_adalan_empire": 1,
          "assignment:monarchy/assignment:reform_levels/assignment:feudalism_vs_autocracy/assignment:reforms/item=text:athenian_monarchy": 1,
          "assignment:monarchy/assignment:reform_levels/assignment:feudalism_vs_autocracy/assignment:reforms/item=text:austria_hungary_reform": 1,
          "assignment:monarchy/assignment:reform_levels/assignment:feudalism_vs_autocracy/assignment:reforms/item=text:byzantine_autocracy": 1,
          "assignment:monarchy/assignment:reform_levels/assignment:feudalism_vs_autocracy/assignment:reforms/item=text:byzantine_late_autocracy": 1,
          "assignment:monarchy/assignment:reform_levels/assignment:feudalism_vs_autocracy/assignment:reforms/item=text:convocation_of_the_tinners_reform": 1,
          "assignment:monarchy/assignment:reform_levels/assignment:feudalism_vs_autocracy/assignment:reforms/item=text:crown_of_castile": 1,
          "assignment:monarchy/assignment:reform_levels/assignment:feudalism_vs_autocracy/assignment:reforms/item=text:crown_of_spain": 1,
          "assignment:monarchy/assignment:reform_levels/assignment:feudalism_vs_autocracy/assignment:reforms/item=text:crusader_kingdom": 1,
          "assignment:monarchy/assignment:reform_levels/assignment:feudalism_vs_autocracy/assignment:reforms/item=text:enlightened_despotism_reform": 1,
          "assignment:monarchy/assignment:reform_levels/assignment:feudalism_vs_autocracy/assignment:reforms/item=text:fu_indian_sultanate_reform": 1,
          "assignment:monarchy/assignment:reform_levels/assignment:feudalism_vs_autocracy/assignment:reforms/item=text:fu_janissary_autocracy": 1,
          "assignment:monarchy/assignment:reform_levels/assignment:feudalism_vs_autocracy/assignment:reforms/item=text:fu_ottoman_government": 1,
          "assignment:monarchy/assignment:reform_levels/assignment:feudalism_vs_autocracy/assignment:reforms/item=text:fu_sultanate_of_rum_and_cairo": 1,
          "assignment:monarchy/assignment:reform_levels/assignment:feudalism_vs_autocracy/assignment:reforms/item=text:german_kaiserreich": 1,
          "assignment:monarchy/assignment:reform_levels/assignment:feudalism_vs_autocracy/assignment:reforms/item=text:khaganate": 1,
          "assignment:monarchy/assignment:reform_levels/assignment:feudalism_vs_autocracy/assignment:reforms/item=text:me_baroque_monarchy_reform": 1,
          "assignment:monarchy/assignment:reform_levels/assignment:feudalism_vs_autocracy/assignment:reforms/item=text:me_mughal_empire": 1,
          "assignment:monarchy/assignment:reform_levels/assignment:feudalism_vs_autocracy/assignment:reforms/item=text:me_nordmark": 1,
          "assignment:monarchy/assignment:reform_levels/assignment:feudalism_vs_autocracy/assignment:reforms/item=text:plantagenet_monarchy": 1,
          "assignment:monarchy/assignment:reform_levels/assignment:feudalism_vs_autocracy/assignment:reforms/item=text:religious_monarchy": 1,
          "assignment:monarchy/assignment:reform_levels/assignment:feudalism_vs_autocracy/assignment:reforms/item=text:sisterhood_of_jeanne_darc_reform": 1,
          "assignment:monarchy/assignment:reform_levels/assignment:feudalism_vs_autocracy/assignment:reforms/item=text:timurid_empire": 1,
          "assignment:monarchy/assignment:reform_levels/assignment:feudalism_vs_autocracy/assignment:reforms/item=text:timurid_empire_upgraded": 1,
          "assignment:monarchy/assignment:reform_levels/assignment:feudalism_vs_autocracy/assignment:reforms/item=text:timurid_governor": 1,
          "assignment:monarchy/assignment:reform_levels/assignment:feudalism_vs_autocracy/assignment:reforms/item=text:timurid_governor_upgraded": 1,
          "assignment:monarchy/assignment:reform_levels/assignment:feudalism_vs_autocracy/assignment:reforms/item=text:timurid_prince": 1,
          "assignment:monarchy/assignment:reform_levels/assignment:feudalism_vs_autocracy/assignment:reforms/item=text:timurid_semi_horde": 1,
          "assignment:monarchy/assignment:reform_levels/assignment:feudalism_vs_autocracy/assignment:reforms/item=text:tudor_monarchy": 1,
          "assignment:monarchy/assignment:reform_levels/assignment:feudalism_vs_autocracy/assignment:reforms/item=text:turko_hellenic_autocracy": 1,
          "assignment:monarchy/assignment:reform_levels/assignment:feudalism_vs_autocracy/assignment:reforms/item=text:tynwald_reform": 1,
          "assignment:monarchy/assignment:reform_levels/assignment:feudalism_vs_autocracy/assignment:reforms/item=text:welsh_principality_reform": 1,
          "assignment:monarchy/assignment:reform_levels/assignment:feudalism_vs_autocracy/assignment:reforms/item=text:west_slavic_monarchy": 1,
          "assignment:monarchy/assignment:reform_levels/assignment:growth_of_administration/assignment:reforms/item=text:ME_reform_chaghatai_literature": 1,
          "assignment:monarchy/assignment:reform_levels/assignment:growth_of_administration/assignment:reforms/item=text:ara_consulate_of_the_sea": 1,
          "assignment:monarchy/assignment:reform_levels/assignment:growth_of_administration/assignment:reforms/item=text:incan_administration_reform": 1,
          "assignment:monarchy/assignment:reform_levels/assignment:growth_of_administration/assignment:reforms/item=text:me_hofkammer_reform": 1,
          "assignment:monarchy/assignment:reform_levels/assignment:growth_of_administration/assignment:reforms/item=text:tur_custodian_holy_city_reform": 1,
          "assignment:monarchy/assignment:reform_levels/assignment:hereditary_vs_nobility/assignment:reforms/item=text:ME_caliphate_feudal_theocracy": 1,
          "assignment:monarchy/assignment:reform_levels/assignment:hereditary_vs_nobility/assignment:reforms/item=text:ME_caliphate_iqta": 1,
          "assignment:monarchy/assignment:reform_levels/assignment:hereditary_vs_nobility/assignment:reforms/item=text:SOS_advanced_tactics": 1,
          "assignment:monarchy/assignment:reform_levels/assignment:hereditary_vs_nobility/assignment:reforms/item=text:aztec_society_reform": 1,
          "assignment:monarchy/assignment:reform_levels/assignment:hereditary_vs_nobility/assignment:reforms/item=text:incan_society_reform": 1,
          "assignment:monarchy/assignment:reform_levels/assignment:hereditary_vs_nobility/assignment:reforms/item=text:maya_society_reform": 1,
          "assignment:monarchy/assignment:reform_levels/assignment:hereditary_vs_nobility/assignment:reforms/item=text:mil_secret_council": 1,
          "assignment:monarchy/assignment:reform_levels/assignment:hereditary_vs_nobility/assignment:reforms/item=text:mughal_government_me": 1,
          "assignment:monarchy/assignment:reform_levels/assignment:hereditary_vs_nobility/assignment:reforms/item=text:mughal_government_me_modifier_buff": 1,
          "assignment:monarchy/assignment:reform_levels/assignment:hereditary_vs_nobility/assignment:reforms/item=text:sharia_reform": 1,
          "assignment:monarchy/assignment:reform_levels/assignment:military_doctrines/assignment:reforms/item=text:EE_FRA_gendarmes_reform": 1,
          "assignment:monarchy/assignment:reform_levels/assignment:separation_of_power/assignment:reforms/item=text:EE_Global_Celtic_Empire": 1,
          "assignment:monarchy/assignment:reform_levels/assignment:separation_of_power/assignment:reforms/item=text:EE_Raabsolute_Monarchy": 1,
          "assignment:monarchy/assignment:reform_levels/assignment:state_and_religion/assignment:reforms/item=text:ME_enlist_the_help_of_sufi_orders": 1,
          "assignment:monarchy/assignment:reform_levels/assignment:state_and_religion/assignment:reforms/item=text:ME_enlist_the_help_of_sufi_orders_ADU": 1,
          "assignment:republic/assignment:legacy_government/item=text:athenian_republic_legacy": 1,
          "assignment:republic/assignment:legacy_government/item=text:greek_league": 1,
          "assignment:republic/assignment:reform_levels/assignment:economical_matters_republic/assignment:reforms/item=text:EE_curtail_the_burghers_reform": 1,
          "assignment:republic/assignment:reform_levels/assignment:economical_matters_republic/assignment:reforms/item=text:EE_modernize_industrial_sector": 1,
          "assignment:republic/assignment:reform_levels/assignment:federalism_vs_unitarism_vs_confederacy/assignment:reforms/item=text:citizen_soldiers_reform": 1,
          "assignment:republic/assignment:reform_levels/assignment:federalism_vs_unitarism_vs_confederacy/assignment:reforms/item=text:fu_canton_administration": 1,
          "assignment:republic/assignment:reform_levels/assignment:federalism_vs_unitarism_vs_confederacy/assignment:reforms/item=text:institutionalized_repbulican_army_reform": 1,
          "assignment:republic/assignment:reform_levels/assignment:federalism_vs_unitarism_vs_confederacy/assignment:reforms/item=text:mil_sforza_administration": 1,
          "assignment:republic/assignment:reform_levels/assignment:frequent_elections_vs_consolidation_of_power/assignment:reforms/item=text:EE_factional_politics_reform": 1,
          "assignment:republic/assignment:reform_levels/assignment:frequent_elections_vs_consolidation_of_power/assignment:reforms/item=text:EE_frequent_elections_reform": 1,
          "assignment:republic/assignment:reform_levels/assignment:guiding_principle_of_administration/assignment:reforms/item=text:federal_governorship_reform": 1,
          "assignment:republic/assignment:reform_levels/assignment:guiding_principle_of_administration/assignment:reforms/item=text:mil_secret_council": 1,
          "assignment:republic/assignment:reform_levels/assignment:guiding_principle_of_administration/assignment:reforms/item=text:orangist_stadholders_reform": 1,
          "assignment:republic/assignment:reform_levels/assignment:office_selection/assignment:reforms/item=text:direct_majority_rule_reform": 1,
          "assignment:republic/assignment:reform_levels/assignment:office_selection/assignment:reforms/item=text:electoral_college_reform": 1,
          "assignment:republic/assignment:reform_levels/assignment:office_selection/assignment:reforms/item=text:nov_republican_guard_reform": 1,
          "assignment:republic/assignment:reform_levels/assignment:oligarchy_merchant_class_noble_elite/assignment:reforms/item=text:RHN_democratic_capitalism": 1,
          "assignment:republic/assignment:reform_levels/assignment:oligarchy_merchant_class_noble_elite/assignment:reforms/item=text:SOS_advanced_tactics": 1,
          "assignment:republic/assignment:reform_levels/assignment:oligarchy_merchant_class_noble_elite/assignment:reforms/item=text:athenian_republic": 1,
          "assignment:republic/assignment:reform_levels/assignment:oligarchy_merchant_class_noble_elite/assignment:reforms/item=text:fu_fleet_with_a_state_reform": 1,
          "assignment:republic/assignment:reform_levels/assignment:oligarchy_merchant_class_noble_elite/assignment:reforms/item=text:greek_league_reform": 1,
          "assignment:republic/assignment:reform_levels/assignment:oligarchy_merchant_class_noble_elite/assignment:reforms/item=text:nov_commercial_law": 1,
          "assignment:republic/assignment:reform_levels/assignment:oligarchy_merchant_class_noble_elite/assignment:reforms/item=text:timurid_stratocracy": 1,
          "assignment:republic/assignment:reform_levels/assignment:parliamentary_vs_presidential/assignment:reforms/item=text:federalism_reform": 1,
          "assignment:republic/assignment:reform_levels/assignment:parliamentary_vs_presidential/assignment:reforms/item=text:supremacy_constitution_reform": 1,
          "assignment:republic/assignment:reform_levels/assignment:question_of_dictatorship/assignment:reforms/item=text:EE_federal_senate_reform": 1,
          "assignment:republic/assignment:reform_levels/assignment:question_of_dictatorship/assignment:reforms/item=text:EE_reinforce_republican_values_reform": 1,
          "assignment:republic/assignment:reform_levels/assignment:question_of_dictatorship/assignment:reforms/item=text:EE_strengthen_executive_powers_reform": 1,
          "assignment:republic/assignment:reform_levels/assignment:question_of_dictatorship/assignment:reforms/item=text:become_rev_empire_reform": 1,
          "assignment:republic/assignment:reform_levels/assignment:question_of_dictatorship/assignment:reforms/item=text:fu_declare_pirate_empire_reform": 1,
          "assignment:republic/assignment:reform_levels/assignment:question_of_dictatorship/assignment:reforms/item=text:legislative_office_selection_reform": 1,
          "assignment:republic/assignment:reform_levels/assignment:question_of_dictatorship/assignment:reforms/item=text:vice_presidential_system_reform": 1,
          "assignment:republic/assignment:reform_levels/assignment:republican_virtues/assignment:reforms/item=text:sharia_reform": 1,
          "assignment:theocracy/assignment:reform_levels/assignment:internal_vs_external_mission/assignment:reforms/item=text:SOS_advanced_tactics": 1,
          "assignment:theocracy/assignment:reform_levels/assignment:internal_vs_external_mission/assignment:reforms/item=text:sharia_reform": 1,
          "assignment:theocracy/assignment:reform_levels/assignment:secularization/assignment:reforms/item=text:empowered_papal_state_reform": 1,
          "assignment:theocracy/assignment:reform_levels/assignment:theocratic_leadership/assignment:reforms/item=text:ME_bektashi_order_reform": 1,
          "assignment:theocracy/assignment:reform_levels/assignment:theocratic_leadership/assignment:reforms/item=text:ME_sufi_order_reform": 1,
          "assignment:theocracy/assignment:reform_levels/assignment:theocratic_leadership/assignment:reforms/item=text:RHN_holy_capitalism": 1,
          "assignment:theocracy/assignment:reform_levels/assignment:theocratic_leadership/assignment:reforms/item=text:aju_hydraulic_empire": 1,
          "assignment:theocracy/assignment:reform_levels/assignment:theocratic_leadership/assignment:reforms/item=text:fu_order_of_saint_joan_reform": 1,
          "assignment:tribal/assignment:reform_levels/assignment:tribal_administration/assignment:reforms/item=text:ME_Celtica_tribal_federation": 1,
          "assignment:tribal/assignment:reform_levels/assignment:tribal_administration/assignment:reforms/item=text:ME_tribal_federation_steppe_horde": 1,
          "assignment:tribal/assignment:reform_levels/assignment:tribal_administration/assignment:reforms/item=text:aztec_society_reform": 1,
          "assignment:tribal/assignment:reform_levels/assignment:tribal_administration/assignment:reforms/item=text:incan_society_reform": 1,
          "assignment:tribal/assignment:reform_levels/assignment:tribal_administration/assignment:reforms/item=text:maya_society_reform": 1,
          "assignment:tribal/assignment:reform_levels/assignment:tribal_cultural_values/assignment:reforms/item=text:EE_civil_society_reform": 1,
          "assignment:tribal/assignment:reform_levels/assignment:tribal_cultural_values/assignment:reforms/item=text:sharia_reform": 1,
          "assignment:tribal/assignment:reform_levels/assignment:tribal_modernization/assignment:reforms/item=text:EE_Modernize_economy": 1,
          "assignment:tribal/assignment:reform_levels/assignment:tribal_reformation/assignment:reforms/item=text:EE_Unleash_Tribal_Horde": 1
        },
        "right_only": {}
      },
      "conflicts": [],
      "scalar_reductions": [],
      "diagnostics": [],
      "timings": {
        "view_ms": 5,
        "merge_ms": 55,
        "comparison_ms": 13,
        "copy_through_definitions": 1,
        "structured_definitions": 4,
        "comparison_reused_definitions": 3,
        "comparison_normalized_definitions": 4,
        "matcher_ns": 26747250,
        "pcs_ns": 8718477,
        "policy_ns": 54356
      }
    },
    {
      "case_id": "3635635014",
      "snapshot_id": "b1f12d633dd249e644a0205708e8c23898d990eb8eea8d43134ff78188ef61f7",
      "relative_path": "common/scripted_effects/zzz_foch_scripted_effects.txt",
      "module_prefix": "common/scripted_effects",
      "content_family": "common/scripted_effects",
      "source_mod_ids": [
        "2164202838",
        "1596815683"
      ],
      "legacy_verdict": "diverges_ast",
      "legacy_accepted": false,
      "status": "manual_resolution_required",
      "publishable": false,
      "policies": {
        "merge_key_source": "assignment_key",
        "nested_merge_key_source": "assignment_key",
        "scalar": "conflict",
        "list": "union",
        "one_sided_removal": "remove",
        "block": "recursive",
        "boolean": "and",
        "block_patch": "union",
        "named_container": "conflict",
        "edit_wins_over_remove": false
      },
      "view_content_ids": {
        "base": "7f8176418415903d3e86fef52374c56d05cda31d7ba3d019a51c6edbc6f1246a",
        "left": "811b3523b79971421faf7b275e6f2a1de9b8bf9e0625d032dcc0ed5d1e2fa466",
        "right": "f5d03158ef356c3b2dd6cab66a37629b87175fc9df181101807ce35898b541fe",
        "human": "cc46ede86a9ec1f3111c6de8435412ed776a77dd1bdd3f14303fefcf8725e710"
      },
      "candidate_semantic_content_id": "6f6d814b114bf8331ec80812167e2381d0355cbc7ff28dd62de08eda3cce90aa",
      "base_definitions": 797,
      "active_definitions": 849,
      "missing_top_level_keys": [],
      "extra_top_level_keys": [],
      "semantic_diff_from_human": {
        "left_atoms": 28066,
        "right_atoms": 28066,
        "shared_atoms": 28066,
        "left_only": {},
        "right_only": {}
      },
      "conflicts": [
        {
          "kind": "policy",
          "detail": "definition `NED_auxilliary_effect`: 2 control-flow finding(s) require review: left:$/NED_auxilliary_effect[0]/add_age_modifier[0]/else[0], output:$/NED_auxilliary_effect[0]/add_age_modifier[0]/else[0]"
        },
        {
          "kind": "policy",
          "detail": "definition `TUN_leo_africanus_spawn`: 2 control-flow finding(s) require review: left:$/TUN_leo_africanus_spawn[0]/else[1], output:$/TUN_leo_africanus_spawn[0]/else[1]"
        },
        {
          "kind": "policy",
          "detail": "definition `set_new_colonization_region`: 1 control-flow finding(s) require review: left:unprovable Clausewitz control-flow structure: `else_if` branch requires exactly one block `limit`"
        }
      ],
      "scalar_reductions": [],
      "diagnostics": [],
      "timings": {
        "view_ms": 53,
        "merge_ms": 27684,
        "comparison_ms": 1256,
        "copy_through_definitions": 485,
        "structured_definitions": 364,
        "comparison_reused_definitions": 1489,
        "comparison_normalized_definitions": 149,
        "matcher_ns": 8548576,
        "pcs_ns": 90236370,
        "policy_ns": 583580
      }
    },
    {
      "case_id": "3635635014",
      "snapshot_id": "b1f12d633dd249e644a0205708e8c23898d990eb8eea8d43134ff78188ef61f7",
      "relative_path": "common/scripted_triggers/zzz_foch_scripted_triggers.txt",
      "module_prefix": "common/scripted_triggers",
      "content_family": "common/scripted_triggers",
      "source_mod_ids": [
        "2164202838",
        "1596815683"
      ],
      "legacy_verdict": "diverges_ast",
      "legacy_accepted": false,
      "status": "accepted_equivalent",
      "publishable": true,
      "policies": {
        "merge_key_source": "assignment_key",
        "nested_merge_key_source": "assignment_key",
        "scalar": "conflict",
        "list": "union",
        "one_sided_removal": "remove",
        "block": "recursive",
        "boolean": "and",
        "block_patch": "boolean_or",
        "named_container": "conflict",
        "edit_wins_over_remove": false
      },
      "view_content_ids": {
        "base": "40c4fac70c9c91f518b8f9d8a3b6e7a0e6f37ac17280bb1dc7fd156c9ca477dd",
        "left": "3dd93c4ee4349fd2fae8c4059c10ea5f9e813cc9902519fb9761f3f349e032d4",
        "right": "996746e01f918085b51ca19792c9705086c5931dfac8e353bba063b05c168b07",
        "human": "943299fe6a0943af2f065fef7f9cf58185df4f2b806d5ecd2d68a74d76022363"
      },
      "candidate_semantic_content_id": "92cf936b6c7424d12a3db7e12d25ea894653d19c815ae69a15b7014e2a05b505",
      "base_definitions": 2507,
      "active_definitions": 539,
      "missing_top_level_keys": [],
      "extra_top_level_keys": [],
      "semantic_diff_from_human": {
        "left_atoms": 24932,
        "right_atoms": 24932,
        "shared_atoms": 24932,
        "left_only": {},
        "right_only": {}
      },
      "conflicts": [],
      "scalar_reductions": [],
      "diagnostics": [],
      "timings": {
        "view_ms": 10,
        "merge_ms": 534,
        "comparison_ms": 740,
        "copy_through_definitions": 497,
        "structured_definitions": 42,
        "comparison_reused_definitions": 3029,
        "comparison_normalized_definitions": 12,
        "matcher_ns": 787080,
        "pcs_ns": 9760598,
        "policy_ns": 54235
      }
    }
  ]
}